best/__init__.py
best/integration/__init__.py
best/unit/__init__.py
best/unit/conftest.py
best/unit/test_glue_session.py
best/unit/test_glue_session_demo.py
best/unit/test_session_apis.py
awscert-10.7.8.dist-info/LICENSE.txt
awscert-10.7.8.dist-info/METADATA
awscert-10.7.8.dist-info/WHEEL
awscert-10.7.8.dist-info/top_level.txt
awscert-10.7.8.dist-info/RECORD
